{
  "permalink": "/blog/welcome",
  "source": "@site/blog/2023-05-20-welcome/index.md",
  "title": "Welcome!",
  "description": "First blog post.",
  "date": "2023-05-20T10:00:00.000Z",
  "formattedDate": "May 20, 2023",
  "tags": [
    {
      "label": "hello",
      "permalink": "/blog/tags/hello"
    },
    {
      "label": "docusaurus-v2",
      "permalink": "/blog/tags/docusaurus-v-2"
    }
  ],
  "readingTime": 0.04,
  "hasTruncateMarker": true,
  "authors": [
    {
      "name": "Will",
      "title": "Creator of the IT KB.",
      "url": "https://github.com/BassJamm?tab=repositories"
    }
  ],
  "frontMatter": {
    "title": "Welcome!",
    "description": "First blog post.",
    "slug": "welcome",
    "date": "2023-05-20T10:00",
    "authors": [
      {
        "name": "Will",
        "title": "Creator of the IT KB.",
        "url": "https://github.com/BassJamm?tab=repositories"
      }
    ],
    "tags": [
      "hello",
      "docusaurus-v2"
    ],
    "image": "https://i.imgur.com/mErPwqL.png",
    "hide_table_of_contents": false
  },
  "prevItem": {
    "title": "Microsoft Defender for Endpoint Woes",
    "permalink": "/blog/Defender-for-Endpoint-Woes"
  }
}